[
  {
    "origen": "FLV",
    "contexto": "Página 152",
    "mensaje": "Request failed with status code 500",
    "url": "https://www3.animeflv.net/browse?page=152",
    "timestamp": "2025-08-16T23:40:51.952Z"
  },
  {
    "origen": "FLV",
    "contexto": "Página 151",
    "mensaje": "Request failed with status code 500",
    "url": "https://www3.animeflv.net/browse?page=151",
    "timestamp": "2025-08-16T23:40:51.953Z"
  },
  {
    "origen": "FLV",
    "contexto": "Página 153",
    "mensaje": "Request failed with status code 500",
    "url": "https://www3.animeflv.net/browse?page=153",
    "timestamp": "2025-08-16T23:40:51.953Z"
  },
  {
    "origen": "FLV",
    "contexto": "Página 154",
    "mensaje": "Request failed with status code 500",
    "url": "https://www3.animeflv.net/browse?page=154",
    "timestamp": "2025-08-16T23:40:51.969Z"
  },
  {
    "origen": "FLV",
    "contexto": "Página 156",
    "mensaje": "Request failed with status code 500",
    "url": "https://www3.animeflv.net/browse?page=156",
    "timestamp": "2025-08-16T23:40:52.170Z"
  },
  {
    "origen": "FLV",
    "contexto": "Página 155",
    "mensaje": "Request failed with status code 500",
    "url": "https://www3.animeflv.net/browse?page=155",
    "timestamp": "2025-08-16T23:40:52.171Z"
  },
  {
    "origen": "FLV",
    "contexto": "Página 157",
    "mensaje": "Request failed with status code 500",
    "url": "https://www3.animeflv.net/browse?page=157",
    "timestamp": "2025-08-16T23:40:52.171Z"
  },
  {
    "origen": "FLV",
    "contexto": "Página 158",
    "mensaje": "Request failed with status code 500",
    "url": "https://www3.animeflv.net/browse?page=158",
    "timestamp": "2025-08-16T23:40:52.196Z"
  },
  {
    "origen": "FLV",
    "contexto": "Página 159",
    "mensaje": "Request failed with status code 500",
    "url": "https://www3.animeflv.net/browse?page=159",
    "timestamp": "2025-08-16T23:40:52.196Z"
  },
  {
    "origen": "FLV",
    "contexto": "Página 161",
    "mensaje": "Request failed with status code 500",
    "url": "https://www3.animeflv.net/browse?page=161",
    "timestamp": "2025-08-16T23:40:52.197Z"
  },
  {
    "origen": "FLV",
    "contexto": "Página 160",
    "mensaje": "Request failed with status code 500",
    "url": "https://www3.animeflv.net/browse?page=160",
    "timestamp": "2025-08-16T23:40:52.197Z"
  },
  {
    "origen": "FLV",
    "contexto": "Página 162",
    "mensaje": "Request failed with status code 500",
    "url": "https://www3.animeflv.net/browse?page=162",
    "timestamp": "2025-08-16T23:40:52.197Z"
  },
  {
    "origen": "FLV",
    "contexto": "Página 163",
    "mensaje": "Request failed with status code 500",
    "url": "https://www3.animeflv.net/browse?page=163",
    "timestamp": "2025-08-16T23:40:52.197Z"
  },
  {
    "origen": "FLV",
    "contexto": "Página 164",
    "mensaje": "Request failed with status code 500",
    "url": "https://www3.animeflv.net/browse?page=164",
    "timestamp": "2025-08-16T23:40:52.197Z"
  },
  {
    "origen": "FLV",
    "contexto": "Página 165",
    "mensaje": "Request failed with status code 500",
    "url": "https://www3.animeflv.net/browse?page=165",
    "timestamp": "2025-08-16T23:40:52.198Z"
  },
  {
    "origen": "FLV",
    "contexto": "Página 166",
    "mensaje": "Request failed with status code 500",
    "url": "https://www3.animeflv.net/browse?page=166",
    "timestamp": "2025-08-16T23:40:52.198Z"
  },
  {
    "origen": "FLV",
    "contexto": "Página 167",
    "mensaje": "Request failed with status code 500",
    "url": "https://www3.animeflv.net/browse?page=167",
    "timestamp": "2025-08-16T23:40:52.198Z"
  },
  {
    "origen": "FLV",
    "contexto": "Página 168",
    "mensaje": "Request failed with status code 500",
    "url": "https://www3.animeflv.net/browse?page=168",
    "timestamp": "2025-08-16T23:40:52.198Z"
  },
  {
    "origen": "FLV",
    "contexto": "Página 169",
    "mensaje": "Request failed with status code 500",
    "url": "https://www3.animeflv.net/browse?page=169",
    "timestamp": "2025-08-16T23:40:52.198Z"
  },
  {
    "origen": "FLV",
    "contexto": "Página 171",
    "mensaje": "Request failed with status code 500",
    "url": "https://www3.animeflv.net/browse?page=171",
    "timestamp": "2025-08-16T23:40:52.198Z"
  },
  {
    "origen": "FLV",
    "contexto": "Página 170",
    "mensaje": "Request failed with status code 500",
    "url": "https://www3.animeflv.net/browse?page=170",
    "timestamp": "2025-08-16T23:40:52.199Z"
  },
  {
    "origen": "FLV",
    "contexto": "Página 172",
    "mensaje": "Request failed with status code 500",
    "url": "https://www3.animeflv.net/browse?page=172",
    "timestamp": "2025-08-16T23:40:52.199Z"
  },
  {
    "origen": "FLV",
    "contexto": "Página 173",
    "mensaje": "Request failed with status code 500",
    "url": "https://www3.animeflv.net/browse?page=173",
    "timestamp": "2025-08-16T23:40:52.202Z"
  },
  {
    "origen": "FLV",
    "contexto": "anime:Getter Robo Arc",
    "mensaje": "Request failed with status code 404",
    "url": "https://www3.animeflv.net/anime/getter-robo-arc",
    "timestamp": "2025-08-16T23:40:58.664Z"
  },
  {
    "origen": "FLV",
    "contexto": "anime:Yami Shibai 8",
    "mensaje": "Request failed with status code 404",
    "url": "https://www3.animeflv.net/anime/yami-shibai-8",
    "timestamp": "2025-08-16T23:40:59.241Z"
  },
  {
    "origen": "FLV",
    "contexto": "anime:Rail Romanesque",
    "mensaje": "Request failed with status code 404",
    "url": "https://www3.animeflv.net/anime/rail-romanesque",
    "timestamp": "2025-08-16T23:40:59.845Z"
  },
  {
    "origen": "FLV",
    "contexto": "anime:Yami Shibai 7",
    "mensaje": "Request failed with status code 404",
    "url": "https://www3.animeflv.net/anime/yami-shibai-7",
    "timestamp": "2025-08-16T23:41:01.159Z"
  },
  {
    "origen": "FLV",
    "contexto": "anime:Yami Shibai 6",
    "mensaje": "Request failed with status code 404",
    "url": "https://www3.animeflv.net/anime/yami-shibai-6",
    "timestamp": "2025-08-16T23:41:02.619Z"
  },
  {
    "origen": "FLV",
    "contexto": "anime:Yami Shibai 5th Season",
    "mensaje": "Request failed with status code 404",
    "url": "https://www3.animeflv.net/anime/yami-shibai-5th-season",
    "timestamp": "2025-08-16T23:41:04.335Z"
  },
  {
    "origen": "FLV",
    "contexto": "anime:Yami Shibai 4th Season",
    "mensaje": "Request failed with status code 404",
    "url": "https://www3.animeflv.net/anime/yami-shibai-4th-season",
    "timestamp": "2025-08-16T23:41:04.771Z"
  },
  {
    "origen": "FLV",
    "contexto": "anime:Yami Shibai 3rd Season",
    "mensaje": "Request failed with status code 404",
    "url": "https://www3.animeflv.net/anime/yami-shibai-3rd-season",
    "timestamp": "2025-08-16T23:41:06.780Z"
  },
  {
    "origen": "FLV",
    "contexto": "anime:Yami Shibai 2",
    "mensaje": "Request failed with status code 404",
    "url": "https://www3.animeflv.net/anime/yami-shibai-2",
    "timestamp": "2025-08-16T23:41:10.043Z"
  },
  {
    "origen": "FLV",
    "contexto": "anime:Break Blade (2014)",
    "mensaje": "Request failed with status code 404",
    "url": "https://www3.animeflv.net/anime/break-blade-2014",
    "timestamp": "2025-08-16T23:41:10.508Z"
  },
  {
    "origen": "FLV",
    "contexto": "anime:Kimi no Iru Machi Uchi ga Kita Machi",
    "mensaje": "Request failed with status code 404",
    "url": "https://www3.animeflv.net/anime/kimi-no-iru-machi-uchi-ga-kita-machi",
    "timestamp": "2025-08-16T23:41:10.854Z"
  },
  {
    "origen": "FLV",
    "contexto": "anime:Super Sonico the Animation",
    "mensaje": "Request failed with status code 404",
    "url": "https://www3.animeflv.net/anime/super-sonico-the-animation",
    "timestamp": "2025-08-16T23:41:11.067Z"
  },
  {
    "origen": "FLV",
    "contexto": "anime:Yami Shibai",
    "mensaje": "Request failed with status code 404",
    "url": "https://www3.animeflv.net/anime/yami-shibai",
    "timestamp": "2025-08-16T23:41:11.856Z"
  },
  {
    "origen": "FLV",
    "contexto": "anime:Kimi no Iru Machi",
    "mensaje": "Request failed with status code 404",
    "url": "https://www3.animeflv.net/anime/kimi-no-iru-machi",
    "timestamp": "2025-08-16T23:41:11.878Z"
  },
  {
    "origen": "FLV",
    "contexto": "anime:Yuyushiki",
    "mensaje": "Request failed with status code 404",
    "url": "https://www3.animeflv.net/anime/yuyushiki",
    "timestamp": "2025-08-16T23:41:12.372Z"
  },
  {
    "origen": "FLV",
    "contexto": "anime:Haiyore! Nyaruko-san W",
    "mensaje": "Request failed with status code 404",
    "url": "https://www3.animeflv.net/anime/haiyore-nyaruko-san-w",
    "timestamp": "2025-08-16T23:41:12.452Z"
  },
  {
    "origen": "FLV",
    "contexto": "anime:Hyakka Ryouran: Samurai Bride",
    "mensaje": "Request failed with status code 404",
    "url": "https://www3.animeflv.net/anime/hyakka-ryouran-samurai-bride",
    "timestamp": "2025-08-16T23:41:12.520Z"
  },
  {
    "origen": "FLV",
    "contexto": "anime:Uta no Prince-sama: Maji Love 2000%",
    "mensaje": "Request failed with status code 404",
    "url": "https://www3.animeflv.net/anime/uta-no-prince-sama-maji-love-2000",
    "timestamp": "2025-08-16T23:41:12.588Z"
  },
  {
    "origen": "FLV",
    "contexto": "anime:Amnesia",
    "mensaje": "Request failed with status code 404",
    "url": "https://www3.animeflv.net/anime/amnesia",
    "timestamp": "2025-08-16T23:41:12.862Z"
  },
  {
    "origen": "FLV",
    "contexto": "anime:Cuticle Detective Inaba",
    "mensaje": "Request failed with status code 404",
    "url": "https://www3.animeflv.net/anime/cuticle-detective-inaba",
    "timestamp": "2025-08-16T23:41:12.971Z"
  },
  {
    "origen": "FLV",
    "contexto": "anime:Muv-Luv Alternative: Total Eclipse",
    "mensaje": "Request failed with status code 404",
    "url": "https://www3.animeflv.net/anime/muv-luv-alternative-total-eclipse",
    "timestamp": "2025-08-16T23:41:13.991Z"
  },
  {
    "origen": "FLV",
    "contexto": "anime:Tari Tari",
    "mensaje": "Request failed with status code 404",
    "url": "https://www3.animeflv.net/anime/tari-tari",
    "timestamp": "2025-08-16T23:41:14.011Z"
  },
  {
    "origen": "FLV",
    "contexto": "anime:La Storia Della Arcana Famiglia",
    "mensaje": "Request failed with status code 404",
    "url": "https://www3.animeflv.net/anime/la-storia-della-arcana-famiglia",
    "timestamp": "2025-08-16T23:41:14.041Z"
  },
  {
    "origen": "FLV",
    "contexto": "anime:Haiyoru! Nyaruko-san",
    "mensaje": "Request failed with status code 404",
    "url": "https://www3.animeflv.net/anime/haiyoru-nyaruko-san",
    "timestamp": "2025-08-16T23:41:14.191Z"
  },
  {
    "origen": "FLV",
    "contexto": "anime:Medaka Box",
    "mensaje": "Request failed with status code 404",
    "url": "https://www3.animeflv.net/anime/medaka-box",
    "timestamp": "2025-08-16T23:41:14.229Z"
  },
  {
    "origen": "FLV",
    "contexto": "anime:Kimi no Iru Machi: Tasogare Kousaten",
    "mensaje": "Request failed with status code 404",
    "url": "https://www3.animeflv.net/anime/kimi-no-iru-machi-tasogare-kousaten",
    "timestamp": "2025-08-16T23:41:14.458Z"
  },
  {
    "origen": "FLV",
    "contexto": "anime:Eiyuu Densetsu: Sora no Kiseki The Animation",
    "mensaje": "Request failed with status code 404",
    "url": "https://www3.animeflv.net/anime/eiyuu-densetsu-sora-no-kiseki-the-animation",
    "timestamp": "2025-08-16T23:41:14.994Z"
  },
  {
    "origen": "FLV",
    "contexto": "anime:Uta no Prince sama: Maji Love 1000%",
    "mensaje": "Request failed with status code 404",
    "url": "https://www3.animeflv.net/anime/uta-no-prince-sama-maji-love-1000",
    "timestamp": "2025-08-16T23:41:15.443Z"
  },
  {
    "origen": "FLV",
    "contexto": "anime:Towa no Quon",
    "mensaje": "Request failed with status code 404",
    "url": "https://www3.animeflv.net/anime/towa-no-quon",
    "timestamp": "2025-08-16T23:41:15.524Z"
  },
  {
    "origen": "FLV",
    "contexto": "anime:Seikon no Qwaser II",
    "mensaje": "Request failed with status code 404",
    "url": "https://www3.animeflv.net/anime/seikon-no-qwaser-ii",
    "timestamp": "2025-08-16T23:41:15.734Z"
  },
  {
    "origen": "FLV",
    "contexto": "anime:Sket Dance",
    "mensaje": "Request failed with status code 404",
    "url": "https://www3.animeflv.net/anime/sket-dance",
    "timestamp": "2025-08-16T23:41:15.849Z"
  },
  {
    "origen": "FLV",
    "contexto": "anime:Level E",
    "mensaje": "Request failed with status code 404",
    "url": "https://www3.animeflv.net/anime/level-e",
    "timestamp": "2025-08-16T23:41:16.048Z"
  },
  {
    "origen": "FLV",
    "contexto": "anime:Mazinkaiser SKL",
    "mensaje": "Request failed with status code 404",
    "url": "https://www3.animeflv.net/anime/mazinkaiser-skl",
    "timestamp": "2025-08-16T23:41:16.259Z"
  },
  {
    "origen": "FLV",
    "contexto": "anime:Kami Nomi zo Shiru Sekai",
    "mensaje": "Request failed with status code 404",
    "url": "https://www3.animeflv.net/anime/kami-nomi-zo-shiru-sekai",
    "timestamp": "2025-08-16T23:41:16.325Z"
  },
  {
    "origen": "FLV",
    "contexto": "anime:Shinryaku! Ika Musume",
    "mensaje": "Request failed with status code 404",
    "url": "https://www3.animeflv.net/anime/shinryaku-ika-musume",
    "timestamp": "2025-08-16T23:41:16.337Z"
  },
  {
    "origen": "FLV",
    "contexto": "anime:Hyakka Ryouran: Samurai Girls",
    "mensaje": "Request failed with status code 404",
    "url": "https://www3.animeflv.net/anime/hyakka-ryoran",
    "timestamp": "2025-08-16T23:41:16.573Z"
  },
  {
    "origen": "FLV",
    "contexto": "anime:Break Blade",
    "mensaje": "Request failed with status code 404",
    "url": "https://www3.animeflv.net/anime/break-blade",
    "timestamp": "2025-08-16T23:41:16.737Z"
  },
  {
    "origen": "FLV",
    "contexto": "anime:Seikon no Qwaser",
    "mensaje": "Request failed with status code 404",
    "url": "https://www3.animeflv.net/anime/seikon-no-qwaser",
    "timestamp": "2025-08-16T23:41:17.065Z"
  },
  {
    "origen": "FLV",
    "contexto": "anime:Tegami Bachi",
    "mensaje": "Request failed with status code 404",
    "url": "https://www3.animeflv.net/anime/tegami-bachi",
    "timestamp": "2025-08-16T23:41:17.415Z"
  },
  {
    "origen": "FLV",
    "contexto": "anime:Cannan",
    "mensaje": "Request failed with status code 404",
    "url": "https://www3.animeflv.net/anime/cannan",
    "timestamp": "2025-08-16T23:41:17.520Z"
  },
  {
    "origen": "FLV",
    "contexto": "anime:Needless",
    "mensaje": "Request failed with status code 404",
    "url": "https://www3.animeflv.net/anime/needless",
    "timestamp": "2025-08-16T23:41:17.522Z"
  },
  {
    "origen": "FLV",
    "contexto": "anime:Tears to Tiara",
    "mensaje": "Request failed with status code 404",
    "url": "https://www3.animeflv.net/anime/tears-to-tiara",
    "timestamp": "2025-08-16T23:41:17.726Z"
  },
  {
    "origen": "FLV",
    "contexto": "anime:Skip Beat",
    "mensaje": "Request failed with status code 404",
    "url": "https://www3.animeflv.net/anime/skip-beat",
    "timestamp": "2025-08-16T23:41:18.245Z"
  },
  {
    "origen": "FLV",
    "contexto": "anime:Hokuto no Ken Raou Gaiden Ten no Haou",
    "mensaje": "Request failed with status code 404",
    "url": "https://www3.animeflv.net/anime/hokuto-no-ken-raou-gaiden-ten-no-haou",
    "timestamp": "2025-08-16T23:41:18.292Z"
  },
  {
    "origen": "FLV",
    "contexto": "anime:Special A",
    "mensaje": "Request failed with status code 404",
    "url": "https://www3.animeflv.net/anime/special-a",
    "timestamp": "2025-08-16T23:41:18.731Z"
  },
  {
    "origen": "FLV",
    "contexto": "anime:Mnemosyne",
    "mensaje": "Request failed with status code 404",
    "url": "https://www3.animeflv.net/anime/mnemosyne",
    "timestamp": "2025-08-16T23:41:18.894Z"
  },
  {
    "origen": "FLV",
    "contexto": "anime:Shugo Chara!",
    "mensaje": "Request failed with status code 404",
    "url": "https://www3.animeflv.net/anime/shugo-chara",
    "timestamp": "2025-08-16T23:41:19.195Z"
  },
  {
    "origen": "FLV",
    "contexto": "anime:Hokuto no Ken: Raoh Gaiden Gekitou-hen",
    "mensaje": "Request failed with status code 404",
    "url": "https://www3.animeflv.net/anime/hokuto-no-ken-raoh-gaiden-gekitou-hen",
    "timestamp": "2025-08-16T23:41:19.498Z"
  },
  {
    "origen": "FLV",
    "contexto": "anime:Hayate no Gotoku!",
    "mensaje": "Request failed with status code 404",
    "url": "https://www3.animeflv.net/anime/hayate-no-gotoku",
    "timestamp": "2025-08-16T23:41:19.875Z"
  },
  {
    "origen": "FLV",
    "contexto": "anime:Hokuto no Ken: Raoh Gaiden Junai-hen",
    "mensaje": "Request failed with status code 404",
    "url": "https://www3.animeflv.net/anime/hokuto-no-ken-raoh-gaiden-junai-hen",
    "timestamp": "2025-08-16T23:41:20.726Z"
  },
  {
    "origen": "FLV",
    "contexto": "anime:Aria the Animation",
    "mensaje": "Request failed with status code 404",
    "url": "https://www3.animeflv.net/anime/aria-the-animation",
    "timestamp": "2025-08-16T23:41:21.006Z"
  },
  {
    "origen": "FLV",
    "contexto": "anime:Eyeshield 21",
    "mensaje": "Request failed with status code 404",
    "url": "https://www3.animeflv.net/anime/eyeshield-21",
    "timestamp": "2025-08-16T23:41:21.276Z"
  }
]